{
  "investor_key": "LiLu",
  "investor_name_cn": "李录",
  "investor_name": "Li Lu",
  "fund": "Himalaya Capital Management",
  "cik": "0001709323",
  "color": "#8b5cf6",
  "report_date": "2025-12-31",
  "filing_date": "2026-02-17",
  "accession": "0002043585-26-000011",
  "quarter": "2025Q4",
  "total_value": 3568876223,
  "holdings": [
    {
      "issuer": "ALPHABET INC",
      "cusip": "02079K107",
      "value_usd": 796052900,
      "shares": 2543300,
      "share_type": "SH",
      "put_call": "",
      "title_class": "CAP STK CL C",
      "weight_pct": 22.30542193841728
    },
    {
      "issuer": "ALPHABET INC",
      "cusip": "02079K305",
      "value_usd": 769217940,
      "shares": 2451300,
      "share_type": "SH",
      "put_call": "",
      "title_class": "CAP STK CL A",
      "weight_pct": 21.553505695789998
    },
    {
      "issuer": "BK OF AMERICA CORP",
      "cusip": "060505104",
      "value_usd": 573726285,
      "shares": 10431387,
      "share_type": "SH",
      "put_call": "",
      "title_class": "COM",
      "weight_pct": 16.075824689647693
    },
    {
      "issuer": "PDD HOLDINGS INC",
      "cusip": "722304102",
      "value_usd": 522501120,
      "shares": 4608000,
      "share_type": "SH",
      "put_call": "",
      "title_class": "SPONSORED ADS",
      "weight_pct": 14.640494299933584
    },
    {
      "issuer": "BERKSHIRE HATHAWAY INC DEL",
      "cusip": "084670702",
      "value_usd": 451253535,
      "shares": 897749,
      "share_type": "SH",
      "put_call": "",
      "title_class": "CL B NEW",
      "weight_pct": 12.644135206815212
    },
    {
      "issuer": "EAST WEST BANCORP INC",
      "cusip": "27579R104",
      "value_usd": 312034089,
      "shares": 2776351,
      "share_type": "SH",
      "put_call": "",
      "title_class": "COM",
      "weight_pct": 8.743202888042553
    },
    {
      "issuer": "OCCIDENTAL PETE CORP",
      "cusip": "674599105",
      "value_usd": 60302480,
      "shares": 1466500,
      "share_type": "SH",
      "put_call": "",
      "title_class": "COM",
      "weight_pct": 1.6896769804280207
    },
    {
      "issuer": "CROCS INC",
      "cusip": "227046109",
      "value_usd": 53720158,
      "shares": 628159,
      "share_type": "SH",
      "put_call": "",
      "title_class": "COM",
      "weight_pct": 1.5052401552565697
    },
    {
      "issuer": "APPLE INC",
      "cusip": "037833100",
      "value_usd": 30067716,
      "shares": 110600,
      "share_type": "SH",
      "put_call": "",
      "title_class": "COM",
      "weight_pct": 0.8424981456690884
    }
  ]
}